pkg/__init__.py
rskeyring/__init__.py
rskeyring/rskeyring.cp38-win_amd64.pyd
rskeyring/rskeyring.pyd
tests/__init__.py
tests/lib_unittest.py
rskeyring-0.1.2.2.dist-info/LICENSE
rskeyring-0.1.2.2.dist-info/METADATA
rskeyring-0.1.2.2.dist-info/WHEEL
rskeyring-0.1.2.2.dist-info/top_level.txt
rskeyring-0.1.2.2.dist-info/RECORD
