Metadata-Version: 2.1
Name: rskeyring
Version: 0.1.2.2
Summary: A C-level keyring module bind from the Rust programming language (crates.io)
Home-page: https://github.com/DK26/pyrust-keyring
Author: David Krasnitsky
Author-email: dikaveman@gmail.com
License: UNKNOWN
Platform: UNKNOWN
Classifier: Programming Language :: Python :: 3
Classifier: Programming Language :: Rust
Classifier: Intended Audience :: Developers
Classifier: License :: OSI Approved :: MIT License
Classifier: Operating System :: OS Independent
Requires-Python: >=3.8
